datasets_private/__init__.py
datasets_private/dataset_private.py
datasets_private/datasets/BostonHousing.csv
datasets_private/datasets/heartdisease.csv
datasets_private/datasets/iris.csv
datasets_private/datasets/penguins.csv
datasets_private/datasets/titanic.csv
dataset_private-1.0.3.dist-info/METADATA
dataset_private-1.0.3.dist-info/WHEEL
dataset_private-1.0.3.dist-info/top_level.txt
dataset_private-1.0.3.dist-info/RECORD
