Metadata-Version: 2.1
Name: dataset-private
Version: 1.0.3
Summary: A package for getting datasets from package
Author: tmptmp
Author-email: tmptmp@tmptmp.com
